server.py
mseep_rootdata_mcp_server-0.1.4.dist-info/METADATA
mseep_rootdata_mcp_server-0.1.4.dist-info/WHEEL
mseep_rootdata_mcp_server-0.1.4.dist-info/entry_points.txt
mseep_rootdata_mcp_server-0.1.4.dist-info/top_level.txt
mseep_rootdata_mcp_server-0.1.4.dist-info/RECORD
