Metadata-Version: 2.4
Name: mseep-rootdata-mcp-server
Version: 0.1.4
Summary: MCP server for RootData API integration
Author-email: mseep <support@skydeck.ai>
Requires-Python: >=3.10
Requires-Dist: httpx>=0.28.1
Requires-Dist: mcp[cli]>=1.3.0
Requires-Dist: python-dotenv>=1.0.1
